fortuna/.DS_Store
fortuna/__init__.py
fortuna/calib_model/.DS_Store
fortuna/calib_model/__init__.py
fortuna/calib_model/base.py
fortuna/calib_model/calib_config/__init__.py
fortuna/calib_model/calib_config/base.py
fortuna/calib_model/calib_config/checkpointer.py
fortuna/calib_model/calib_config/monitor.py
fortuna/calib_model/calib_config/optimizer.py
fortuna/calib_model/calib_config/processor.py
fortuna/calib_model/calib_model_calibrator.py
fortuna/calib_model/classification.py
fortuna/calib_model/predictive/.DS_Store
fortuna/calib_model/predictive/__init__.py
fortuna/calib_model/predictive/base.py
fortuna/calib_model/predictive/classification.py
fortuna/calib_model/predictive/regression.py
fortuna/calib_model/regression.py
fortuna/calibration/__init__.py
fortuna/calibration/calibrator.py
fortuna/calibration/state.py
fortuna/conformal/__init__.py
fortuna/conformal/classification.py
fortuna/conformal/regression.py
fortuna/data/.DS_Store
fortuna/data/__init__.py
fortuna/data/loader.py
fortuna/distribution/.DS_Store
fortuna/distribution/__init__.py
fortuna/distribution/base.py
fortuna/distribution/gaussian.py
fortuna/make_data.py
fortuna/make_model.py
fortuna/metric/.DS_Store
fortuna/metric/__init__.py
fortuna/metric/classification.py
fortuna/metric/regression.py
fortuna/model/.DS_Store
fortuna/model/__init__.py
fortuna/model/cnn.py
fortuna/model/lenet.py
fortuna/model/mlp.py
fortuna/model/model_manager/.DS_Store
fortuna/model/model_manager/__init__.py
fortuna/model/model_manager/base.py
fortuna/model/model_manager/classification.py
fortuna/model/model_manager/regression.py
fortuna/model/model_manager/state.py
fortuna/model/resnet.py
fortuna/model/wideresnet.py
fortuna/output_calibrator/.DS_Store
fortuna/output_calibrator/__init__.py
fortuna/output_calibrator/classification.py
fortuna/output_calibrator/output_calib_manager/.DS_Store
fortuna/output_calibrator/output_calib_manager/__init__.py
fortuna/output_calibrator/output_calib_manager/base.py
fortuna_uq-0.1.0.dist-info/LICENSE
fortuna_uq-0.1.0.dist-info/WHEEL
fortuna_uq-0.1.0.dist-info/METADATA
fortuna_uq-0.1.0.dist-info/RECORD
