Metadata-Version: 2.1
Name: fortuna-uq
Version: 0.1.0
Summary: A Library for Uncertainty Quantification.
License: Apache-2.0
Author: Gianluca Detommaso
Author-email: gianluca.detommaso@gmail.com
Requires-Python: >=3.8,<3.11
Classifier: License :: OSI Approved :: Apache Software License
Classifier: Programming Language :: Python :: 3
Classifier: Programming Language :: Python :: 3.8
Classifier: Programming Language :: Python :: 3.9
Classifier: Programming Language :: Python :: 3.10
Requires-Dist: Sphinx (>=5.3.0,<6.0.0)
Requires-Dist: flax (>=0.6.2,<0.7.0)
Requires-Dist: ipykernel (>=6.17.1,<7.0.0)
Requires-Dist: jupyter (>=1.0.0,<2.0.0)
Requires-Dist: matplotlib (>=3.6.2,<4.0.0)
Requires-Dist: nbsphinx (>=0.8.10,<0.9.0)
Requires-Dist: nbsphinx-link (>=1.3.0,<2.0.0)
Requires-Dist: numpy (>=1.23.4,<2.0.0)
Requires-Dist: optax (>=0.1.3,<0.2.0)
Requires-Dist: sphinx-autodoc-typehints (>=1.19.5,<2.0.0)
Requires-Dist: sphinx-gallery (>=0.11.1,<0.12.0)
Requires-Dist: sphinxawesome-theme (>=3.3.7,<4.0.0)
Requires-Dist: tensorflow (>=2.11.0,<3.0.0)
Requires-Dist: tensorflow-datasets (>=4.7.0,<5.0.0)
Requires-Dist: tqdm (>=4.64.1,<5.0.0)
Project-URL: Documentation, https://aws-fortuna.readthedocs.io/en/latest/
